pytest_api_cov/__init__.py
pytest_api_cov/cli.py
pytest_api_cov/config.py
pytest_api_cov/frameworks.py
pytest_api_cov/models.py
pytest_api_cov/plugin.py
pytest_api_cov/pytest_flags.py
pytest_api_cov/report.py
pytest_api_cov-1.2.2.dist-info/METADATA
pytest_api_cov-1.2.2.dist-info/WHEEL
pytest_api_cov-1.2.2.dist-info/entry_points.txt
pytest_api_cov-1.2.2.dist-info/licenses/LICENSE
pytest_api_cov-1.2.2.dist-info/RECORD
