Metadata-Version: 2.4
Name: pytest-api-cov
Version: 1.2.2
Summary: Pytest Plugin to provide API Coverage statistics for Python Web Frameworks
Project-URL: Source, https://github.com/BarnabasG/api-coverage
Author-email: Barnaby Gill <barnabasgill@gmail.com>
License: Apache-2.0
License-File: LICENSE
Requires-Python: >=3.10
Requires-Dist: fastapi>=0.68.0
Requires-Dist: flask>=2.0.0
Requires-Dist: httpx>=0.20.0
Requires-Dist: pydantic>=2.0.0
Requires-Dist: pytest>=6.0.0
Requires-Dist: rich>=10.0.0
Requires-Dist: starlette>=0.14.0
Requires-Dist: tomli>=1.2.0
